celltk/__init__.py
celltk/apply.py
celltk/caller.py
celltk/caller_parallel.py
celltk/command.py
celltk/labeledarray/LICENSE
celltk/labeledarray/README.md
celltk/labeledarray/__init__.py
celltk/labeledarray/labeledarray/__init__.py
celltk/labeledarray/labeledarray/labeledarray.py
celltk/labeledarray/labeledarray/temp.npz
celltk/labeledarray/labeledarray/test.npz
celltk/labeledarray/labeledarray/utils.py
celltk/postprocess.py
celltk/postprocess_operation.py
celltk/preprocess.py
celltk/preprocess_operation.py
celltk/segment.py
celltk/segment_operation.py
celltk/subdetect.py
celltk/subdetect_operation.py
celltk/track.py
celltk/track_operation.py
celltk/utils/__init__.py
celltk/utils/_model_builder.py
celltk/utils/_munkres.py
celltk/utils/_mutinfo.py
celltk/utils/binary_ops.py
celltk/utils/concave_seg.py
celltk/utils/cp_functions.py
celltk/utils/dlevel_set.py
celltk/utils/file_io.py
celltk/utils/filters.py
celltk/utils/fish_detect.py
celltk/utils/global_holder.py
celltk/utils/imreg.py
celltk/utils/labels_handling.py
celltk/utils/mi_align.py
celltk/utils/miopt_align.py
celltk/utils/morphsnakes.py
celltk/utils/pairwise.py
celltk/utils/parser.py
celltk/utils/postprocess_utils.py
celltk/utils/preprocess_utils.py
celltk/utils/rolling_ball.py
celltk/utils/shading_correction.py
celltk/utils/stitch_utils.py
celltk/utils/subdetect_utils.py
celltk/utils/tfutils.py
celltk/utils/traces.py
celltk/utils/track_utils.py
celltk/utils/unet_predict.py
celltk/utils/util.py
celltk/utils/wavelet_bgr.py
celltk-0.3.dist-info/entry_points.txt
celltk-0.3.dist-info/LICENSE
celltk-0.3.dist-info/WHEEL
celltk-0.3.dist-info/METADATA
celltk-0.3.dist-info/RECORD
